{
  "$schema": "https://developer.microsoft.com/json-schemas/fabric/item/report/definition/visualContainer/2.5.0/schema.json",
  "name": "95b3d673e63fc6621f11",
  "position": {
    "x": 49.6048632218845,
    "y": 93.373860182370819,
    "z": 1000,
    "height": 592.34042553191489,
    "width": 258.72340425531917,
    "tabOrder": 1000
  },
  "visual": {
    "visualType": "shape",
    "objects": {
      "shape": [
        {
          "properties": {
            "tileShape": {
              "expr": {
                "Literal": {
                  "Value": "'rectangleRounded'"
                }
              }
            },
            "rectangleRoundedCurve": {
              "expr": {
                "Literal": {
                  "Value": "8L"
                }
              }
            }
          }
        }
      ],
      "rotation": [
        {
          "properties": {
            "shapeAngle": {
              "expr": {
                "Literal": {
                  "Value": "0L"
                }
              }
            }
          }
        }
      ],
      "fill": [
        {
          "properties": {
            "fillColor": {
              "solid": {
                "color": {
                  "expr": {
                    "Literal": {
                      "Value": "'#FFFFFF'"
                    }
                  }
                }
              }
            }
          },
          "selector": {
            "id": "default"
          }
        }
      ],
      "outline": [
        {
          "properties": {
            "show": {
              "expr": {
                "Literal": {
                  "Value": "false"
                }
              }
            }
          }
        }
      ],
      "text": [
        {
          "properties": {
            "show": {
              "expr": {
                "Literal": {
                  "Value": "true"
                }
              }
            }
          }
        },
        {
          "properties": {
            "text": {
              "expr": {
                "Literal": {
                  "Value": "'Filtros'"
                }
              }
            },
            "fontColor": {
              "solid": {
                "color": {
                  "expr": {
                    "Literal": {
                      "Value": "'#1F2A44'"
                    }
                  }
                }
              }
            },
            "horizontalAlignment": {
              "expr": {
                "Literal": {
                  "Value": "'left'"
                }
              }
            },
            "verticalAlignment": {
              "expr": {
                "Literal": {
                  "Value": "'top'"
                }
              }
            },
            "fontSize": {
              "expr": {
                "Literal": {
                  "Value": "15D"
                }
              }
            },
            "bold": {
              "expr": {
                "Literal": {
                  "Value": "false"
                }
              }
            },
            "fontFamily": {
              "expr": {
                "Literal": {
                  "Value": "'wf_standard-font, helvetica, arial, sans-serif'"
                }
              }
            }
          },
          "selector": {
            "id": "default"
          }
        }
      ],
      "glow": [
        {
          "properties": {
            "show": {
              "expr": {
                "Literal": {
                  "Value": "false"
                }
              }
            }
          }
        }
      ]
    },
    "visualContainerObjects": {
      "title": [
        {
          "properties": {
            "show": {
              "expr": {
                "Literal": {
                  "Value": "true"
                }
              }
            },
            "text": {
              "expr": {
                "Literal": {
                  "Value": "''"
                }
              }
            },
            "titleWrap": {
              "expr": {
                "Literal": {
                  "Value": "false"
                }
              }
            }
          }
        }
      ],
      "divider": [
        {
          "properties": {
            "show": {
              "expr": {
                "Literal": {
                  "Value": "false"
                }
              }
            },
            "ignorePadding": {
              "expr": {
                "Literal": {
                  "Value": "false"
                }
              }
            }
          }
        }
      ],
      "subTitle": [
        {
          "properties": {
            "show": {
              "expr": {
                "Literal": {
                  "Value": "false"
                }
              }
            }
          }
        }
      ],
      "visualHeader": [
        {
          "properties": {
            "show": {
              "expr": {
                "Literal": {
                  "Value": "false"
                }
              }
            }
          }
        }
      ],
      "visualLink": [
        {
          "properties": {
            "show": {
              "expr": {
                "Literal": {
                  "Value": "false"
                }
              }
            }
          }
        }
      ]
    },
    "drillFilterOtherVisuals": true
  },
  "howCreated": "InsertVisualButton"
}