{
  "$schema": "https://developer.microsoft.com/json-schemas/fabric/item/report/definition/visualContainer/2.5.0/schema.json",
  "name": "c10301ea8dbe8055a20e",
  "position": {
    "x": 57.710233029381982,
    "y": 372.52279635258361,
    "z": 5000,
    "height": 73.9209726443769,
    "width": 237.32522796352583,
    "tabOrder": 5000
  },
  "visual": {
    "visualType": "slicer",
    "query": {
      "queryState": {
        "Values": {
          "projections": [
            {
              "field": {
                "Column": {
                  "Expression": {
                    "SourceRef": {
                      "Entity": "dados_vendas_sql_treino xlsx"
                    }
                  },
                  "Property": "produto"
                }
              },
              "queryRef": "dados_vendas_sql_treino xlsx.produto",
              "nativeQueryRef": "produto",
              "active": true
            }
          ]
        }
      }
    },
    "objects": {
      "data": [
        {
          "properties": {
            "mode": {
              "expr": {
                "Literal": {
                  "Value": "'Dropdown'"
                }
              }
            },
            "isInvertedSelectionMode": {
              "expr": {
                "Literal": {
                  "Value": "true"
                }
              }
            }
          }
        }
      ],
      "general": [
        {
          "properties": {}
        }
      ],
      "header": [
        {
          "properties": {
            "text": {
              "expr": {
                "Literal": {
                  "Value": "'Data - Mês'"
                }
              }
            },
            "textSize": {
              "expr": {
                "Literal": {
                  "Value": "15D"
                }
              }
            },
            "outlineStyle": {
              "expr": {
                "Literal": {
                  "Value": "0D"
                }
              }
            },
            "show": {
              "expr": {
                "Literal": {
                  "Value": "false"
                }
              }
            }
          }
        }
      ],
      "selection": [
        {
          "properties": {
            "selectAllCheckboxEnabled": {
              "expr": {
                "Literal": {
                  "Value": "true"
                }
              }
            },
            "singleSelect": {
              "expr": {
                "Literal": {
                  "Value": "false"
                }
              }
            }
          }
        }
      ]
    },
    "visualContainerObjects": {
      "title": [
        {
          "properties": {
            "show": {
              "expr": {
                "Literal": {
                  "Value": "true"
                }
              }
            },
            "text": {
              "expr": {
                "Literal": {
                  "Value": "'Produto'"
                }
              }
            },
            "fontSize": {
              "expr": {
                "Literal": {
                  "Value": "12D"
                }
              }
            },
            "fontColor": {
              "solid": {
                "color": {
                  "expr": {
                    "Literal": {
                      "Value": "'#1F2A44'"
                    }
                  }
                }
              }
            }
          }
        }
      ],
      "border": [
        {
          "properties": {
            "show": {
              "expr": {
                "Literal": {
                  "Value": "false"
                }
              }
            },
            "radius": {
              "expr": {
                "Literal": {
                  "Value": "0D"
                }
              }
            }
          }
        }
      ],
      "visualHeader": [
        {
          "properties": {
            "show": {
              "expr": {
                "Literal": {
                  "Value": "true"
                }
              }
            },
            "foreground": {
              "solid": {
                "color": {
                  "expr": {
                    "Literal": {
                      "Value": "'#1F2A44'"
                    }
                  }
                }
              }
            }
          }
        }
      ]
    },
    "drillFilterOtherVisuals": true
  },
  "filterConfig": {
    "filters": [
      {
        "name": "970aacbc6a206e35122f",
        "field": {
          "Column": {
            "Expression": {
              "SourceRef": {
                "Entity": "dados_vendas_sql_treino xlsx"
              }
            },
            "Property": "produto"
          }
        },
        "type": "Categorical"
      }
    ]
  }
}